PyXA/XABase.py
PyXA/XABaseScriptable.py
PyXA/XAErrors.py
PyXA/XAEvents.py
PyXA/XAProtocols.py
PyXA/XATypes.py
PyXA/__init__.py
PyXA/Additions/Devices.py
PyXA/Additions/Learn.py
PyXA/Additions/Speech.py
PyXA/Additions/UI.py
PyXA/Additions/Utils.py
PyXA/Additions/Web.py
PyXA/Additions/__init__.py
PyXA/apps/AcrobatReader.py
PyXA/apps/Alfred.py
PyXA/apps/Amphetamine.py
PyXA/apps/Arc.py
PyXA/apps/Automator.py
PyXA/apps/Bike.py
PyXA/apps/Calculator.py
PyXA/apps/Calendar.py
PyXA/apps/Cardhop.py
PyXA/apps/Chromium.py
PyXA/apps/Console.py
PyXA/apps/Contacts.py
PyXA/apps/DatabaseEvents.py
PyXA/apps/Dictionary.py
PyXA/apps/Drafts.py
PyXA/apps/Fantastical.py
PyXA/apps/Finder.py
PyXA/apps/Flow.py
PyXA/apps/FontBook.py
PyXA/apps/Hammerspoon.py
PyXA/apps/IINA.py
PyXA/apps/ImageEvents.py
PyXA/apps/Keynote.py
PyXA/apps/Mail.py
PyXA/apps/Maps.py
PyXA/apps/Messages.py
PyXA/apps/Music.py
PyXA/apps/Notes.py
PyXA/apps/Numbers.py
PyXA/apps/OmniOutliner.py
PyXA/apps/OmniWeb.py
PyXA/apps/Pages.py
PyXA/apps/PathFinder.py
PyXA/apps/PhotosApp.py
PyXA/apps/Preview.py
PyXA/apps/QuickTimePlayer.py
PyXA/apps/RStudio.py
PyXA/apps/Reminders.py
PyXA/apps/Safari.py
PyXA/apps/ScriptEditor.py
PyXA/apps/Shortcuts.py
PyXA/apps/Spotify.py
PyXA/apps/Stocks.py
PyXA/apps/SystemEvents.py
PyXA/apps/SystemPreferences.py
PyXA/apps/TV.py
PyXA/apps/Terminal.py
PyXA/apps/TextEdit.py
PyXA/apps/VLC.py
PyXA/apps/__init__.py
PyXA/apps/iTerm.py
PyXA/apps/iWorkApplicationBase.py
tests/__init__.py
tests/test_base_scriptable.py
tests/test_calendar.py
tests/test_contacts.py
tests/test_database_events.py
tests/test_finder.py
tests/test_iwork.py
tests/test_messages.py
tests/test_music.py
tests/test_notes.py
tests/test_omniweb.py
tests/test_reminders.py
tests/test_safari.py
tests/test_shortcuts.py
tests/test_terminal.py
tests/test_textedit.py
mac_pyxa-0.3.0.1.dist-info/LICENSE
mac_pyxa-0.3.0.1.dist-info/METADATA
mac_pyxa-0.3.0.1.dist-info/WHEEL
mac_pyxa-0.3.0.1.dist-info/top_level.txt
mac_pyxa-0.3.0.1.dist-info/RECORD
