Metadata-Version: 2.1
Name: mac-pyxa
Version: 0.3.0.1
Summary: A package for accomplish AppleScript automation tasks using Python syntax.
Home-page: https://github.com/SKaplanOfficial/PyXA
Author: Stephen Kaplan
Author-email: stephen.kaplan@maine.edu
Project-URL: Bug Tracker, https://github.com/SKaplanOfficial/PyXA/issues
Classifier: Programming Language :: Python :: 3
Classifier: License :: OSI Approved :: MIT License
Classifier: Operating System :: OS Independent
Requires-Python: >=3.10
License-File: LICENSE
Requires-Dist: pyobjc-core==9.*
Requires-Dist: pyobjc-framework-AVFoundation==9.*
Requires-Dist: pyobjc-framework-EventKit==9.*
Requires-Dist: pyobjc-framework-Quartz==9.*
Requires-Dist: pyobjc-framework-ScriptingBridge==9.*
Requires-Dist: pyobjc-framework-NaturalLanguage==9.*
Requires-Dist: pyobjc-framework-CoreLocation==9.*
Requires-Dist: pyobjc-framework-Vision==9.*
Requires-Dist: pyobjc-framework-CoreMedia==9.*
Requires-Dist: pyobjc-framework-Photos==9.*
Requires-Dist: pyobjc-framework-Speech==9.*
Requires-Dist: pyobjc-framework-LatentSemanticMapping==9.*
Requires-Dist: pyobjc-framework-ApplicationServices==9.*
Requires-Dist: pyobjc-framework-CoreText==9.*
Requires-Dist: pyobjc-framework-libdispatch==9.*
Requires-Dist: pyobjc-framework-datadetection==9.*
Requires-Dist: requests==2.28.*
Requires-Dist: beautifulsoup4==4.11.*
Requires-Dist: macimg==0.0.3
